MANIFEST.in
README.md
setup.py
stanmo/__init__.py
stanmo/stanmoctl.py
stanmo.egg-info/PKG-INFO
stanmo.egg-info/SOURCES.txt
stanmo.egg-info/dependency_links.txt
stanmo.egg-info/entry_points.txt
stanmo.egg-info/not-zip-safe
stanmo.egg-info/requires.txt
stanmo.egg-info/top_level.txt
stanmo/app/__init__.py
stanmo/app/basemodelspec.py
stanmo/app/config.py
stanmo/app/dbmodel.py
stanmo/app/stanmoapp.py
stanmo/data/churn_apply.csv
stanmo/data/churn_apply_result.csv
stanmo/data/churn_source.csv
stanmo/log/stanmo.log
stanmo/spec/__init__.py
stanmo/spec/churn/__init__.py
stanmo/spec/churn/__init__.pyc
stanmo/spec/churn/churn_result.json
stanmo/spec/churn/churn_source.json
stanmo/spec/churn/churnmodelflask.py
stanmo/spec/churn/churnmodelflask.pyc
stanmo/spec/churn/churnmodelspec.py
stanmo/spec/churn/churnmodelspec.pyc
stanmo/spec/churn/web/static/css/custom.css
stanmo/spec/churn/web/static/js/graphs.js
stanmo/spec/churn/web/static/lib/css/bootstrap.min.css
stanmo/spec/churn/web/static/lib/css/dc.css
stanmo/spec/churn/web/static/lib/css/keen-dashboards.css
stanmo/spec/churn/web/static/lib/css/nv.d3.css
stanmo/spec/churn/web/static/lib/js/bootstrap.min.js
stanmo/spec/churn/web/static/lib/js/d3.js
stanmo/spec/churn/web/static/lib/js/jquery.min.js
stanmo/spec/churn/web/static/lib/js/keen.min.js
stanmo/spec/churn/web/static/lib/js/nv.d3.js
stanmo/spec/churn/web/static/lib/js/queue.js
stanmo/spec/churn/web/templates/index.html
stanmo/test/__init__.py
stanmo/test/stanmo_tutorial.py
stanmo/test/test_stanmo.py