Metadata-Version: 1.0
Name: stanmo
Version: 0.2
Summary: Execution engine for standard business learning models.
Home-page: https://github.com/qiyangduan/stanmo
Author: Duan Qiyang
Author-email: qiyang.duan@qq.com
License: Apache Software License
Platform: UNKNOWN
